{"id": "ihr-priester-lasst-uns-frauen-nicht-ins-leere-rennen", "tag": "Schweiz", "tag2": "Schweiz", "title": "«Ihr Priester, lasst uns Frauen nicht ins Leere rennen»", "text": "\n«Die Zweiklassenkirche ist vorbei. Wir brauchen auch keine Frauenpriesterweihe, keine Kleriker*innen und Laien. Ihr Priester und Diakone, die ihr euch diesen Gedanken verbunden fühlt. Lasst uns Frauen nicht allein ins Leere rennen, schliesst euch zusammen, legt euer ‹höheres Amt› nieder und verwirklicht zusammen mit euren mitarbeitenden Frauen und Männer und allen Getauften die neue – alte Kirche. Wir sind Getaufte, eins in Christus.»\nDas schreibt Monika Schmid in ihrer Kolumne im «Landboten» vom 8. Februar. Die Gemeindeleiterin der katholischen Pfarrei Illnau-Effretikon verweist dabei auf den Brief von Paulus an die Gemeinde von Galatien, der die Vision von Kirche enthielt, dass «alle eins in Christus Jesus» seien. Dies jenseits aller Gegensätze, etwa zwischen Sklaven und Freien, Mann und Frau. (rp)\n\n© Katholisches Medienzentrum, 08.02.2020\nDie Rechte sämtlicher Texte sind beim Katholischen Medienzentrum. Jede Weiterverbreitung ist honorarpflichtig. Die Speicherung in elektronischen Datenbanken ist nicht erlaubt.\n\n\n                            Möchten Sie diesen Artikel in Ihrem Medium weiterverwenden?Hier geht es zur\n                            › Bestellung einzelner Beiträge\n                            von kath.ch.\n                        \n\n\n", "date": "2020-02-08 09:59"}